{
  "lista": [
    {
      "nome_produto": "Abridor de lata",
      "img_produto": "https://localdaimagem.com.br",
      "descricao": "abrir as latas mais facil é o desejo de toda dona de casa"
    },
    {
      "nome_produto": "Abridor de lata",
      "img_produto": "https://localdaimagem.com.br",
      "descricao": "abrir as latas mais facil é o desejo de toda dona de casa"
    },
    {
      "nome_produto": "Abridor de lata",
      "img_produto": "https://localdaimagem.com.br",
      "descricao": "abrir as latas mais facil é o desejo de toda dona de casa"
    },
    {
      "nome_produto": "Abridor de lata",
      "img_produto": "https://localdaimagem.com.br",
      "descricao": "abrir as latas mais facil é o desejo de toda dona de casa"
    },
    {
      "nome_produto": "Abridor de lata",
      "img_produto": "https://localdaimagem.com.br",
      "descricao": "abrir as latas mais facil é o desejo de toda dona de casa"
    },
    {
      "nome_produto": "Abridor de lata",
      "img_produto": "https://localdaimagem.com.br",
      "descricao": "abrir as latas mais facil é o desejo de toda dona de casa"
    }
  ]
}
